tiotrap/__init__.py
tiotrap/tiotrap.py
tiotrap-0.3.3.dist-info/LICENSE
tiotrap-0.3.3.dist-info/WHEEL
tiotrap-0.3.3.dist-info/METADATA
tiotrap-0.3.3.dist-info/RECORD
