Metadata-Version: 2.1
Name: tiotrap
Version: 0.3.3
Summary: Helper For Capturing Text IO Streams like stdout, stderr
Home-page: https://pypi.org/project/tiotrap/
License: BSD-3-Clause
Author: Timothy C. Quinn
Requires-Python: >=3.7.1
Classifier: Development Status :: 4 - Beta
Classifier: Environment :: Console
Classifier: Intended Audience :: System Administrators
Classifier: License :: OSI Approved :: BSD License
Classifier: Operating System :: MacOS :: MacOS X
Classifier: Operating System :: POSIX :: BSD
Classifier: Operating System :: POSIX :: Linux
Classifier: Operating System :: POSIX :: SunOS/Solaris
Classifier: Programming Language :: Python :: 3
Classifier: Programming Language :: Python :: 3 :: Only
Classifier: Programming Language :: Python :: 3.10
Classifier: Programming Language :: Python :: 3.7
Classifier: Programming Language :: Python :: 3.8
Classifier: Programming Language :: Python :: 3.9
Classifier: Topic :: System :: Filesystems
Classifier: Topic :: Utilities
Project-URL: Repository, https://github.com/JavaScriptDude/TextIOTrap
